<?xml version="1.0" encoding="UTF-8"?>
<beans xmlns="http://www.springframework.org/schema/beans"
	xmlns:xsi="http://www.w3.org/2001/XMLSchema-instance"
	xsi:schemaLocation="http://www.springframework.org/schema/beans http://www.springframework.org/schema/beans/spring-beans.xsd">
	<!-- 
	CalcBeanImpl cal=new CalcBeanImpl(4);
	cal.setSu1(30);
	 -->	
	<bean id="cal" class="sample4.CalcBeanImpl">
		<property name="su1">
			<value>30</value>
		</property>
		<constructor-arg>
			<value>4</value>
		</constructor-arg>
	</bean>
	
	<bean id="message" class="sample4.MessageBeanImpl">
		<property name="greeting">
			<value>안녕!</value>
		</property>
		<constructor-arg>
			<value>아이유</value>
		</constructor-arg>
	</bean>
</beans>
